Workbook

Sheet Dashboard
B2: Budget & Finance Dashboard
B5: A premium no-API finance command center for budgets, transactions, recurring expenses, debts, savings, and goals.
B7: Net Worth | E7: Monthly Cash Flow | H7: Savings Rate | K7: Runway | N7: Debt Balance
B11: =SUMIF(Accounts!G:G,"Yes",Accounts!E:E) | E11: =SUMIFS('Transaction Log'!F:F,'Transaction Log'!C:C,"Income",'Transaction Log'!K:K,Settings!B6)-SUMIFS('Transaction Log'!F:F,'Transaction Log'!C:C,"Expense",'Transaction Log'!K:K,Settings!B6) | H11: =IF(SUMIFS('Transaction Log'!F:F,'Transaction Log'!C:C,"Income",'Transaction Log'!K:K,Settings!B6)=0,0,(SUMIFS('Transaction Log'!F:F,'Transaction Log'!C:C,"Income",'Transaction Log'!K:K,Settings!B6)-SUMIFS('Transaction Log'!F:F,'Transaction Log'!C:C,"Expense",'Transaction Log'!K:K,Settings!B6))/SUMIFS('Transaction Log'!F:F,'Transaction Log'!C:C,"Income",'Transaction Log'!K:K,Settings!B6)) | K11: =SUMIFS(Accounts!E:E,Accounts!B:B,"Bank")/Settings!B7 | N11: =SUM('Debt Tracker'!E:E)
B14: Sub-Category | C14: Spent | D14: Budget
B15: Rent / Mortgage | C15: =SUMIFS('Transaction Log'!F:F,'Transaction Log'!E:E,B15,'Transaction Log'!C:C,"Expense",'Transaction Log'!K:K,Settings!B6) | D15: 2200
B16: Groceries | C16: =SUMIFS('Transaction Log'!F:F,'Transaction Log'!E:E,B16,'Transaction Log'!C:C,"Expense",'Transaction Log'!K:K,Settings!B6) | D16: 750
B17: Dining Out | C17: =SUMIFS('Transaction Log'!F:F,'Transaction Log'!E:E,B17,'Transaction Log'!C:C,"Expense",'Transaction Log'!K:K,Settings!B6) | D17: 400
B18: Internet | C18: =SUMIFS('Transaction Log'!F:F,'Transaction Log'!E:E,B18,'Transaction Log'!C:C,"Expense",'Transaction Log'!K:K,Settings!B6) | D18: 75
B19: Mobile Phone | C19: =SUMIFS('Transaction Log'!F:F,'Transaction Log'!E:E,B19,'Transaction Log'!C:C,"Expense",'Transaction Log'!K:K,Settings!B6) | D19: 120
B20: Electric / Water | C20: =SUMIFS('Transaction Log'!F:F,'Transaction Log'!E:E,B20,'Transaction Log'!C:C,"Expense",'Transaction Log'!K:K,Settings!B6) | D20: 155
B21: Gas | C21: =SUMIFS('Transaction Log'!F:F,'Transaction Log'!E:E,B21,'Transaction Log'!C:C,"Expense",'Transaction Log'!K:K,Settings!B6) | D21: 260
B22: Maintenance | C22: =SUMIFS('Transaction Log'!F:F,'Transaction Log'!E:E,B22,'Transaction Log'!C:C,"Expense",'Transaction Log'!K:K,Settings!B6) | D22: 240
B23: Medical | C23: =SUMIFS('Transaction Log'!F:F,'Transaction Log'!E:E,B23,'Transaction Log'!C:C,"Expense",'Transaction Log'!K:K,Settings!B6) | D23: 250
B24: Fitness | C24: =SUMIFS('Transaction Log'!F:F,'Transaction Log'!E:E,B24,'Transaction Log'!C:C,"Expense",'Transaction Log'!K:K,Settings!B6) | D24: 100
B25: Shopping | C25: =SUMIFS('Transaction Log'!F:F,'Transaction Log'!E:E,B25,'Transaction Log'!C:C,"Expense",'Transaction Log'!K:K,Settings!B6) | D25: 600
B26: Entertainment | C26: =SUMIFS('Transaction Log'!F:F,'Transaction Log'!E:E,B26,'Transaction Log'!C:C,"Expense",'Transaction Log'!K:K,Settings!B6) | D26: 250
B27: Streaming / Software | C27: =SUMIFS('Transaction Log'!F:F,'Transaction Log'!E:E,B27,'Transaction Log'!C:C,"Expense",'Transaction Log'!K:K,Settings!B6) | D27: 180
B28: Books / Courses | C28: =SUMIFS('Transaction Log'!F:F,'Transaction Log'!E:E,B28,'Transaction Log'!C:C,"Expense",'Transaction Log'!K:K,Settings!B6) | D28: 250
B29: Brokerage / Retirement | C29: =SUMIFS('Transaction Log'!F:F,'Transaction Log'!E:E,B29,'Transaction Log'!C:C,"Expense",'Transaction Log'!K:K,Settings!B6) | D29: 2000
B30: Auto Loan | C30: =SUMIFS('Transaction Log'!F:F,'Transaction Log'!E:E,B30,'Transaction Log'!C:C,"Expense",'Transaction Log'!K:K,Settings!B6) | D30: 450
B34: Type | C34: Amount
B35: Needs | C35: =SUMIFS('Transaction Log'!F:F,'Transaction Log'!C:C,"Expense",'Transaction Log'!D:D,"Housing",'Transaction Log'!K:K,Settings!B6)+SUMIFS('Transaction Log'!F:F,'Transaction Log'!C:C,"Expense",'Transaction Log'!D:D,"Food",'Transaction Log'!K:K,Settings!B6)+SUMIFS('Transaction Log'!F:F,'Transaction Log'!C:C,"Expense",'Transaction Log'!D:D,"Utilities",'Transaction Log'!K:K,Settings!B6)+SUMIFS('Transaction Log'!F:F,'Transaction Log'!C:C,"Expense",'Transaction Log'!D:D,"Transportation",'Transaction Log'!K:K,Settings!B6)+SUMIFS('Transaction Log'!F:F,'Transaction Log'!C:C,"Expense",'Transaction Log'!D:D,"Health",'Transaction Log'!K:K,Settings!B6)
B36: Wants | C36: =SUMIFS('Transaction Log'!F:F,'Transaction Log'!C:C,"Expense",'Transaction Log'!D:D,"Lifestyle",'Transaction Log'!K:K,Settings!B6)+SUMIFS('Transaction Log'!F:F,'Transaction Log'!C:C,"Expense",'Transaction Log'!D:D,"Subscriptions",'Transaction Log'!K:K,Settings!B6)
B37: Investments | C37: =SUMIFS('Transaction Log'!F:F,'Transaction Log'!C:C,"Investment",'Transaction Log'!K:K,Settings!B6)

Sheet Settings
B2: Settings
B3: Global configuration for the embedded finance engine
A5: Setting | B5: Value | C5: Notes
A6: Currency Symbol | B6: $ | C6: Currency used in labels
A7: Dashboard Month | B7: 2026-05 | C7: Use YYYY-MM
A8: Monthly Essential Expense Estimate | B8: 5400 | C8: Used for runway
A9: Emergency Fund Target Months | B9: 6 | C9: Target months
A10: Budget Strategy | B10: Zero-Based | C10: Zero-Based or Carried Over
A11: Theme | B11: Life OS Mint/Aqua/Lavender | C11: Matches Notion template

Sheet Budget Setup
B2: Budget Setup
B3: Define category and sub-category limits
A5: Category | B5: Sub-Category | C5: Group | D5: Monthly Budget | E5: Priority | F5: Warning Threshold | G5: Hard Limit | H5: Rollover? | I5: Notes
A6: Housing | B6: Rent / Mortgage | C6: Needs | D6: 2200 | E6: High | F6: 0.9 | G6: 1 | H6: No | I6: Primary housing
A7: Food | B7: Groceries | C7: Needs | D7: 750 | E7: High | F7: 0.85 | G7: 1 | H7: No | I7: Groceries
A8: Food | B8: Dining Out | C8: Wants | D8: 400 | E8: Medium | F8: 0.8 | G8: 1 | H8: No | I8: Restaurants
A9: Utilities | B9: Internet | C9: Needs | D9: 75 | E9: High | F9: 0.85 | G9: 1 | H9: No | I9: Internet
A10: Utilities | B10: Mobile Phone | C10: Needs | D10: 120 | E10: High | F10: 0.85 | G10: 1 | H10: No | I10: Phone
A11: Utilities | B11: Electric / Water | C11: Needs | D11: 155 | E11: High | F11: 0.85 | G11: 1 | H11: No | I11: Utilities
A12: Transportation | B12: Gas | C12: Needs | D12: 260 | E12: Medium | F12: 0.85 | G12: 1 | H12: No | I12: Fuel
A13: Transportation | B13: Maintenance | C13: Needs | D13: 240 | E13: Medium | F13: 0.85 | G13: 1 | H13: Yes | I13: Car maintenance
A14: Health | B14: Medical | C14: Needs | D14: 250 | E14: High | F14: 0.85 | G14: 1 | H14: Yes | I14: Medical
A15: Health | B15: Fitness | C15: Needs | D15: 100 | E15: Medium | F15: 0.85 | G15: 1 | H15: No | I15: Gym
A16: Lifestyle | B16: Shopping | C16: Wants | D16: 600 | E16: Medium | F16: 0.8 | G16: 1 | H16: No | I16: Shopping
A17: Lifestyle | B17: Entertainment | C17: Wants | D17: 250 | E17: Low | F17: 0.8 | G17: 1 | H17: No | I17: Entertainment
... A21: Debt | B21: Auto Loan | C21: Debt | D21: 450 | E21: High | F21: 0.9 | G21: 1 | H21: No | I21: Debt payoff

Sheet Recurring Transactions
B2: Recurring Transactions
B3: Configure repeating income, bills, subscriptions, debt payments and investments once
A5: Active? | B5: Name | C5: Type | D5: Category | E5: Sub-Category | F5: Amount | G5: Account | H5: Frequency | I5: Next Date | J5: Day of Month | K5: Auto-Post? | L5: Status | M5: Notes
A6: Yes | B6: Biweekly Paycheck | C6: Income | D6: Income | E6: Salary | F6: 5200 | G6: Chase Checking | H6: Biweekly | I6: 2026-05-15 | J6: 15 | K6: Yes | L6: Planned | M6: Primary salary
A7: Yes | B7: Rent Payment | C7: Expense | D7: Housing | E7: Rent / Mortgage | F7: 2200 | G7: Chase Checking | H7: Monthly | I7: 2026-05-01 | J7: 1 | K7: Yes | L7: Paid | M7: Rent
A8: Yes | B8: Internet Bill | C8: Expense | D8: Utilities | E8: Internet | F8: 75 | G8: Chase Freedom Credit Card | H8: Monthly | I8: 2026-05-08 | J8: 8 | K8: Yes | L8: Paid | M8: Internet
A9: Yes | B9: Mobile Phone Plan | C9: Expense | D9: Utilities | E9: Mobile Phone | F9: 120 | G9: Amex Blue Cash Card | H9: Monthly | I9: 2026-05-12 | J9: 12 | K9: Yes | L9: Paid | M9: Phone
A10: Yes | B10: Streaming Bundle | C10: Expense | D10: Subscriptions | E10: Streaming / Software | F10: 58 | G10: Amex Blue Cash Card | H10: Monthly | I10: 2026-05-15 | J10: 15 | K10: Yes | L10: Paid | M10: Streaming
A11: Yes | B11: Brokerage Auto-Invest | C11: Investment | D11: Investments | E11: Brokerage / Retirement | F11: 1000 | G11: Chase Checking | H11: Monthly | I11: 2026-05-05 | J11: 5 | K11: Yes | L11: Paid | M11: Brokerage
A12: Yes | B12: Roth IRA Contribution | C12: Investment | D12: Investments | E12: Brokerage / Retirement | F12: 500 | G12: Chase Checking | H12: Monthly | I12: 2026-05-05 | J12: 5 | K12: Yes | L12: Paid | M12: Roth IRA
A13: Yes | B13: Car Loan Payment | C13: Debt Payment | D13: Debt | E13: Auto Loan | F13: 450 | G13: Chase Checking | H13: Monthly | I13: 2026-05-18 | J13: 18 | K13: Yes | L13: Pending | M13: Debt payoff

Sheet Transaction Log
B2: Transaction Log
B3: Capture day-to-day income, expenses, transfers, investments and debt payments
A5: Date | B5: Name | C5: Type | D5: Category | E5: Sub-Category | F5: Amount | G5: Account | H5: Payment Method | I5: Status | J5: Recurring Source | K5: Month | L5: Week | M5: Duplicate Check | N5: Notes
A6: 2026-05-01 | B6: May Paycheck 1 | C6: Income | D6: Income | E6: Salary | F6: 5200 | G6: Chase Checking | H6: ACH | I6: Paid | J6: Biweekly Paycheck | K6: =TEXT(A6,"yyyy-mm") | L6: =WEEKNUM(A6) | M6: =IF(COUNTIFS(A:A,A6,B:B,B6,F:F,F6)>1,"⚠ Possible Duplicate","") | N6: First paycheck
A7: 2026-05-01 | B7: Rent Payment | C7: Expense | D7: Housing | E7: Rent / Mortgage | F7: 2200 | G7: Chase Checking | H7: ACH | I7: Paid | J7: Rent Payment | K7: =TEXT(A7,"yyyy-mm") | L7: =WEEKNUM(A7) | M7: =IF(COUNTIFS(A:A,A7,B:B,B7,F:F,F7)>1,"⚠ Possible Duplicate","") | N7: Rent
A8: 2026-05-05 | B8: Brokerage Auto-Invest | C8: Investment | D8: Investments | E8: Brokerage / Retirement | F8: 1000 | G8: Chase Checking | H8: Auto Debit | I8: Paid | J8: Brokerage Auto-Invest | K8: =TEXT(A8,"yyyy-mm") | L8: =WEEKNUM(A8) | M8: =IF(COUNTIFS(A:A,A8,B:B,B8,F:F,F8)>1,"⚠ Possible Duplicate","") | N8: Auto invest
A9: 2026-05-05 | B9: Roth IRA Contribution | C9: Investment | D9: Investments | E9: Brokerage / Retirement | F9: 500 | G9: Chase Checking | H9: Auto Debit | I9: Paid | J9: Roth IRA Contribution | K9: =TEXT(A9,"yyyy-mm") | L9: =WEEKNUM(A9) | M9: =IF(COUNTIFS(A:A,A9,B:B,B9,F:F,F9)>1,"⚠ Possible Duplicate","") | N9: Roth
A10: 2026-05-06 | B10: Costco Groceries | C10: Expense | D10: Food | E10: Groceries | F10: 185 | G10: Amex Blue Cash Card | H10: Credit Card | I10: Paid | K10: =TEXT(A10,"yyyy-mm") | L10: =WEEKNUM(A10) | M10: =IF(COUNTIFS(A:A,A10,B:B,B10,F:F,F10)>1,"⚠ Possible Duplicate","")
A11: 2026-05-08 | B11: Internet Bill | C11: Expense | D11: Utilities | E11: Internet | F11: 75 | G11: Chase Freedom Credit Card | H11: Credit Card | I11: Paid | J11: Internet Bill | K11: =TEXT(A11,"yyyy-mm") | L11: =WEEKNUM(A11) | M11: =IF(COUNTIFS(A:A,A11,B:B,B11,F:F,F11)>1,"⚠ Possible Duplicate","") | N11: Internet
A12: 2026-05-09 | B12: Gas Station | C12: Expense | D12: Transportation | E12: Gas | F12: 62 | G12: Chase Freedom Credit Card | H12: Credit Card | I12: Paid | K12: =TEXT(A12,"yyyy-mm") | L12: =WEEKNUM(A12) | M12: =IF(COUNTIFS(A:A,A12,B:B,B12,F:F,F12)>1,"⚠ Possible Duplicate","")
A13: 2026-05-10 | B13: Dinner Downtown | C13: Expense | D13: Food | E13: Dining Out | F13: 88 | G13: Chase Freedom Credit Card | H13: Credit Card | I13: Paid | K13: =TEXT(A13,"yyyy-mm") | L13: =WEEKNUM(A13) | M13: =IF(COUNTIFS(A:A,A13,B:B,B13,F:F,F13)>1,"⚠ Possible Duplicate","")
A14: 2026-05-11 | B14: Online Course | C14: Expense | D14: Learning | E14: Books / Courses | F14: 149 | G14: Chase Freedom Credit Card | H14: Credit Card | I14: Paid | K14: =TEXT(A14,"yyyy-mm") | L14: =WEEKNUM(A14) | M14: =IF(COUNTIFS(A:A,A14,B:B,B14,F:F,F14)>1,"⚠ Possible Duplicate","")
A15: 2026-05-12 | B15: Mobile Phone Plan | C15: Expense | D15: Utilities | E15: Mobile Phone | F15: 120 | G15: Amex Blue Cash Card | H15: Credit Card | I15: Paid | J15: Mobile Phone Plan | K15: =TEXT(A15,"yyyy-mm") | L15: =WEEKNUM(A15) | M15: =IF(COUNTIFS(A:A,A15,B:B,B15,F:F,F15)>1,"⚠ Possible Duplicate","") | N15: Phone
A16: 2026-05-13 | B16: Trader Joes | C16: Expense | D16: Food | E16: Groceries | F16: 96 | G16: Amex Blue Cash Card | H16: Credit Card | I16: Paid | K16: =TEXT(A16,"yyyy-mm") | L16: =WEEKNUM(A16) | M16: =IF(COUNTIFS(A:A,A16,B:B,B16,F:F,F16)>1,"⚠ Possible Duplicate","")
A17: 2026-05-15 | B17: Streaming Bundle | C17: Expense | D17: Subscriptions | E17: Streaming / Software | F17: 58 | G17: Amex Blue Cash Card | H17: Credit Card | I17: Paid | J17: Streaming Bundle | K17: =TEXT(A17,"yyyy-mm") | L17: =WEEKNUM(A17) | M17: =IF(COUNTIFS(A:A,A17,B:B,B17,F:F,F17)>1,"⚠ Possible Duplicate","") | N17: Streaming
A18: 2026-05-15 | B18: May Paycheck 2 | C18: Income | D18: Income | E18: Salary | F18: 5200 | G18: Chase Checking | H18: ACH | I18: Paid | J18: Biweekly Paycheck | K18: =TEXT(A18,"yyyy-mm") | L18: =WEEKNUM(A18) | M18: =IF(COUNTIFS(A:A,A18,B:B,B18,F:F,F18)>1,"⚠ Possible Duplicate","") | N18: Second paycheck
A19: 2026-05-17 | B19: Target Household | C19: Expense | D19: Lifestyle | E19: Shopping | F19: 210 | G19: Chase Freedom Credit Card | H19: Credit Card | I19: Paid | K19: =TEXT(A19,"yyyy-mm") | L19: =WEEKNUM(A19) | M19: =IF(COUNTIFS(A:A,A19,B:B,B19,F:F,F19)>1,"⚠ Possible Duplicate","")
A20: 2026-05-18 | B20: Car Loan Payment | C20: Debt Payment | D20: Debt | E20: Auto Loan | F20: 450 | G20: Chase Checking | H20: ACH | I20: Paid | J20: Car Loan Payment | K20: =TEXT(A20,"yyyy-mm") | L20: =WEEKNUM(A20) | M20: =IF(COUNTIFS(A:A,A20,B:B,B20,F:F,F20)>1,"⚠ Possible Duplicate","") | N20: Debt
A21: 2026-05-20 | B21: Doctor Visit Copay | C21: Expense | D21: Health | E21: Medical | F21: 45 | G21: Chase Freedom Credit Card | H21: Credit Card | I21: Paid | K21: =TEXT(A21,"yyyy-mm") | L21: =WEEKNUM(A21) | M21: =IF(COUNTIFS(A:A,A21,B:B,B21,F:F,F21)>1,"⚠ Possible Duplicate","")
K22: =IF(A22="","",TEXT(A22,"yyyy-mm")) | L22: =IF(A22="","",WEEKNUM(A22)) | M22: =IF(A22="","",IF(COUNTIFS(A:A,A22,B:B,B22,F:F,F22)>1,"⚠ Possible Duplicate",""))
K23: =IF(A23="","",TEXT(A23,"yyyy-mm")) | L23: =IF(A23="","",WEEKNUM(A23)) | M23: =IF(A23="","",IF(COUNTIFS(A:A,A23,B:B,B23,F:F,F23)>1,"⚠ Possible Duplicate",""))
K24: =IF(A24="","",TEXT(A24,"yyyy-mm")) | L24: =IF(A24="","",WEEKNUM(A24)) | M24: =IF(A24="","",IF(COUNTIFS(A:A,A24,B:B,B24,F:F,F24)>1,"⚠ Possible Duplicate",""))
K25: =IF(A25="","",TEXT(A25,"yyyy-mm")) | L25: =IF(A25="","",WEEKNUM(A25)) | M25: =IF(A25="","",IF(COUNTIFS(A:A,A25,B:B,B25,F:F,F25)>1,"⚠ Possible Duplicate",""))
K26: =IF(A26="","",TEXT(A26,"yyyy-mm")) | L26: =IF(A26="","",WEEKNUM(A26)) | M26: =IF(A26="","",IF(COUNTIFS(A:A,A26,B:B,B26,F:F,F26)>1,"⚠ Possible Duplicate",""))
K27: =IF(A27="","",TEXT(A27,"yyyy-mm")) | L27: =IF(A27="","",WEEKNUM(A27)) | M27: =IF(A27="","",IF(COUNTIFS(A:A,A27,B:B,B27,F:F,F27)>1,"⚠ Possible Duplicate",""))
K28: =IF(A28="","",TEXT(A28,"yyyy-mm")) | L28: =IF(A28="","",WEEKNUM(A28)) | M28: =IF(A28="","",IF(COUNTIFS(A:A,A28,B:B,B28,F:F,F28)>1,"⚠ Possible Duplicate",""))
K29: =IF(A29="","",TEXT(A29,"yyyy-mm")) | L29: =IF(A29="","",WEEKNUM(A29)) | M29: =IF(A29="","",IF(COUNTIFS(A:A,A29,B:B,B29,F:F,F29)>1,"⚠ Possible Duplicate",""))
K30: =IF(A30="","",TEXT(A30,"yyyy-mm")) | L30: =IF(A30="","",WEEKNUM(A30)) | M30: =IF(A30="","",IF(COUNTIFS(A:A,A30,B:B,B30,F:F,F30)>1,"⚠ Possible Duplicate",""))
K31: =IF(A31="","",TEXT(A31,"yyyy-mm")) | L31: =IF(A31="","",WEEKNUM(A31)) | M31: =IF(A31="","",IF(COUNTIFS(A:A,A31,B:B,B31,F:F,F31)>1,"⚠ Possible Duplicate",""))
K32: =IF(A32="","",TEXT(A32,"yyyy-mm")) | L32: =IF(A32="","",WEEKNUM(A32)) | M32: =IF(A32="","",IF(COUNTIFS(A:A,A32,B:B,B32,F:F,F32)>1,"⚠ Possible Duplicate",""))
K33: =IF(A33="","",TEXT(A33,"yyyy-mm")) | L33: =IF(A33="","",WEEKNUM(A33)) | M33: =IF(A33="","",IF(COUNTIFS(A:A,A33,B:B,B33,F:F,F33)>1,"⚠ Possible Duplicate",""))
... K1006: =IF(A1006="","",TEXT(A1006,"yyyy-mm")) | L1006: =IF(A1006="","",WEEKNUM(A1006)) | M1006: =IF(A1006="","",IF(COUNTIFS(A:A,A1006,B:B,B1006,F:F,F1006)>1,"⚠ Possible Duplicate",""))

Sheet Accounts
B2: Accounts
B3: Track bank, wallet, credit card and investment balances
A5: Account | B5: Type | C5: Institution | D5: Opening Balance | E5: Current Balance | F5: Credit Limit | G5: Include in Net Worth? | H5: Utilization | I5: Health | J5: Notes
A6: Chase Checking | B6: Bank | C6: Chase | D6: 6500 | E6: 8250 | G6: Yes | H6: =IF(B6="Credit Card",ABS(E6)/F6,"") | I6: =IF(B6="Credit Card",IF(H6>=0.8,"🔴 High",IF(H6>=0.5,"🟡 Monitor","🟢 Healthy")),"🟢 Healthy") | J6: Primary account
A7: Ally High-Yield Savings | B7: Savings | C7: Ally Bank | D7: 18500 | E7: 21200 | G7: Yes | H7: =IF(B7="Credit Card",ABS(E7)/F7,"") | I7: =IF(B7="Credit Card",IF(H7>=0.8,"🔴 High",IF(H7>=0.5,"🟡 Monitor","🟢 Healthy")),"🟢 Healthy") | J7: Emergency fund
A8: Venmo Wallet | B8: Wallet | C8: Venmo | D8: 420 | E8: 180 | G8: Yes | H8: =IF(B8="Credit Card",ABS(E8)/F8,"") | I8: =IF(B8="Credit Card",IF(H8>=0.8,"🔴 High",IF(H8>=0.5,"🟡 Monitor","🟢 Healthy")),"🟢 Healthy") | J8: Wallet
A9: Chase Freedom Credit Card | B9: Credit Card | C9: Chase | D9: 0 | E9: -1850 | F9: 12000 | G9: Yes | H9: =IF(B9="Credit Card",ABS(E9)/F9,"") | I9: =IF(B9="Credit Card",IF(H9>=0.8,"🔴 High",IF(H9>=0.5,"🟡 Monitor","🟢 Healthy")),"🟢 Healthy") | J9: Rewards card
A10: Amex Blue Cash Card | B10: Credit Card | C10: Amex | D10: 0 | E10: -940 | F10: 15000 | G10: Yes | H10: =IF(B10="Credit Card",ABS(E10)/F10,"") | I10: =IF(B10="Credit Card",IF(H10>=0.8,"🔴 High",IF(H10>=0.5,"🟡 Monitor","🟢 Healthy")),"🟢 Healthy") | J10: Groceries card
A11: Fidelity Brokerage | B11: Investment | C11: Fidelity | D11: 42000 | E11: 48650 | G11: Yes | H11: =IF(B11="Credit Card",ABS(E11)/F11,"") | I11: =IF(B11="Credit Card",IF(H11>=0.8,"🔴 High",IF(H11>=0.5,"🟡 Monitor","🟢 Healthy")),"🟢 Healthy") | J11: Brokerage
A12: Vanguard Roth IRA | B12: Investment | C12: Vanguard | D12: 28500 | E12: 32750 | G12: Yes | H12: =IF(B12="Credit Card",ABS(E12)/F12,"") | I12: =IF(B12="Credit Card",IF(H12>=0.8,"🔴 High",IF(H12>=0.5,"🟡 Monitor","🟢 Healthy")),"🟢 Healthy") | J12: Roth
A13: 401(k) | B13: Investment | C13: Employer Plan | D13: 95000 | E13: 106500 | G13: Yes | H13: =IF(B13="Credit Card",ABS(E13)/F13,"") | I13: =IF(B13="Credit Card",IF(H13>=0.8,"🔴 High",IF(H13>=0.5,"🟡 Monitor","🟢 Healthy")),"🟢 Healthy") | J13: 401k

Sheet Debt Tracker
B2: Debt Tracker
B3: Track debts and compare snowball, avalanche or custom repayment strategies
A5: Debt | B5: Type | C5: Lender | D5: Starting Balance | E5: Current Balance | F5: APR | G5: Minimum Payment | H5: Extra Payment | I5: Strategy | J5: Monthly Payment | K5: Interest This Month | L5: Projected Months | M5: Payoff Status | N5: Notes
A6: Car Loan | B6: Auto Loan | C6: Credit Union | D6: 18500 | E6: 14250 | F6: 0.065 | G6: 390 | H6: 60 | I6: Avalanche | J6: =G6+H6 | K6: =E6*F6/12 | L6: =IF(J6<=K6,"Increase Payment",ROUNDUP(E6/(J6-K6),0)) | M6: =IF(E6<=0,"✅ Paid Off",IF(J6<=K6,"🔴 Payment Too Low","🟡 In Progress")) | N6: Auto loan
A7: Student Loan | B7: Student Loan | C7: Federal Servicer | D7: 32000 | E7: 28500 | F7: 0.048 | G7: 290 | H7: 0 | I7: Snowball | J7: =G7+H7 | K7: =E7*F7/12 | L7: =IF(J7<=K7,"Increase Payment",ROUNDUP(E7/(J7-K7),0)) | M7: =IF(E7<=0,"✅ Paid Off",IF(J7<=K7,"🔴 Payment Too Low","🟡 In Progress")) | N7: Student loan
A8: Credit Card Balance | B8: Credit Card | C8: Chase | D8: 4200 | E8: 1850 | F8: 0.199 | G8: 95 | H8: 150 | I8: Avalanche | J8: =G8+H8 | K8: =E8*F8/12 | L8: =IF(J8<=K8,"Increase Payment",ROUNDUP(E8/(J8-K8),0)) | M8: =IF(E8<=0,"✅ Paid Off",IF(J8<=K8,"🔴 Payment Too Low","🟡 In Progress")) | N8: Revolving

Sheet Savings Goals
B2: Savings Goals
B3: Track sinking funds, emergency fund and financial goals
A5: Goal | B5: Goal Type | C5: Target Amount | D5: Current Amount | E5: Monthly Contribution | F5: Target Date | G5: Progress | H5: Remaining | I5: Months Left | J5: Required Monthly | K5: Status | L5: Notes | P5: Emergency Fund | Q5: Amount
A6: Emergency Fund | B6: Safety | C6: 30000 | D6: 21200 | E6: 850 | F6: 2026-12-31 | G6: =IF(C6=0,0,D6/C6) | H6: =MAX(0,C6-D6) | I6: =MAX(0,DATEDIF(TODAY(),F6,"m")) | J6: =IF(I6=0,H6,H6/I6) | K6: =IF(G6>=1,"✅ Complete",IF(E6>=J6,"🟢 On Track",IF(E6>=J6*0.75,"🟡 Watch","🔴 Needs More"))) | L6: Six months expenses | P6: Current | Q6: =D6
A7: National Parks Vacation | B7: Travel | C7: 6500 | D7: 2300 | E7: 600 | F7: 2026-10-31 | G7: =IF(C7=0,0,D7/C7) | H7: =MAX(0,C7-D7) | I7: =MAX(0,DATEDIF(TODAY(),F7,"m")) | J7: =IF(I7=0,H7,H7/I7) | K7: =IF(G7>=1,"✅ Complete",IF(E7>=J7,"🟢 On Track",IF(E7>=J7*0.75,"🟡 Watch","🔴 Needs More"))) | L7: Travel fund | P7: Remaining | Q7: =H6
A8: Home Down Payment | B8: Major Purchase | C8: 120000 | D8: 38500 | E8: 1500 | F8: 2028-12-31 | G8: =IF(C8=0,0,D8/C8) | H8: =MAX(0,C8-D8) | I8: =MAX(0,DATEDIF(TODAY(),F8,"m")) | J8: =IF(I8=0,H8,H8/I8) | K8: =IF(G8>=1,"✅ Complete",IF(E8>=J8,"🟢 On Track",IF(E8>=J8*0.75,"🟡 Watch","🔴 Needs More"))) | L8: Down payment
A9: Holiday Gifts | B9: Sinking Fund | C9: 2500 | D9: 650 | E9: 250 | F9: 2026-12-01 | G9: =IF(C9=0,0,D9/C9) | H9: =MAX(0,C9-D9) | I9: =MAX(0,DATEDIF(TODAY(),F9,"m")) | J9: =IF(I9=0,H9,H9/I9) | K9: =IF(G9>=1,"✅ Complete",IF(E9>=J9,"🟢 On Track",IF(E9>=J9*0.75,"🟡 Watch","🔴 Needs More"))) | L9: Gifts
A10: New Laptop | B10: Sinking Fund | C10: 2200 | D10: 900 | E10: 250 | F10: 2026-09-30 | G10: =IF(C10=0,0,D10/C10) | H10: =MAX(0,C10-D10) | I10: =MAX(0,DATEDIF(TODAY(),F10,"m")) | J10: =IF(I10=0,H10,H10/I10) | K10: =IF(G10>=1,"✅ Complete",IF(E10>=J10,"🟢 On Track",IF(E10>=J10*0.75,"🟡 Watch","🔴 Needs More"))) | L10: Laptop

Sheet Reports
B2: Reports
B3: Month-over-month trends, spending comparison and category rankings
A5: Month | B5: Income | C5: Expenses | D5: Investments | E5: Savings | F5: Savings Rate
A6: 2026-01 | B6: 10100 | C6: 5150 | D6: 1800 | E6: 3150 | F6: =IF(B6=0,0,E6/B6)
A7: 2026-02 | B7: 10400 | C7: 5480 | D7: 1900 | E7: 3020 | F7: =IF(B7=0,0,E7/B7)
A8: 2026-03 | B8: 10400 | C8: 5325 | D8: 2000 | E8: 3075 | F8: =IF(B8=0,0,E8/B8)
A9: 2026-04 | B9: 10400 | C9: 5700 | D9: 2000 | E9: 2700 | F9: =IF(B9=0,0,E9/B9)
A10: 2026-05 | B10: 10400 | C10: 3239 | D10: 2000 | E10: 5161 | F10: =IF(B10=0,0,E10/B10)

Sheet Smart Calendar
B2: Smart Calendar
B3: Calendar view of recurring and variable transactions
B5: Mon | C5: Tue | D5: Wed | E5: Thu | F5: Fri | G5: Sat | H5: Sun
F6: 1 May Paycheck 1 Rent Payment | G6: 2 | H6: 3
B7: 4 | C7: 5 Brokerage Auto-Invest Roth IRA Contribution | D7: 6 Costco Groceries | E7: 7 | F7: 8 Internet Bill | G7: 9 Gas Station | H7: 10 Dinner Downtown
B8: 11 Online Course | C8: 12 Mobile Phone Plan | D8: 13 Trader Joes | E8: 14 | F8: 15 Streaming Bundle May Paycheck 2 | G8: 16 | H8: 17 Target Household
B9: 18 Car Loan Payment | C9: 19 | D9: 20 Doctor Visit Copay | E9: 21 | F9: 22 | G9: 23 | H9: 24
B10: 25 | C10: 26 | D10: 27 | E10: 28 | F10: 29 | G10: 30 | H10: 31

Sheet Instructions
B2: How to Use This Workbook
B3: Built for embedding inside a Notion Budget / Finance dashboard
A5: Step | B5: Action | C5: Details
A6: 1 | B6: Set assumptions | C6: Go to Settings and confirm currency, month, budget strategy and emergency assumptions.
A7: 2 | B7: Define budget | C7: Go to Budget Setup and configure categories, sub-categories, budget limits and thresholds.
A8: 3 | B8: Configure recurring | C8: Go to Recurring Transactions and enter salary, bills, subscriptions, debt payments and investments once.
A9: 4 | B9: Log transactions | C9: Go to Transaction Log and record day-to-day income, expenses, transfers, investments and debt payments.
A10: 5 | B10: Track debt | C10: Go to Debt Tracker and update balances, APR, minimums, extra payments and strategy.
A11: 6 | B11: Track savings | C11: Go to Savings Goals and update current amounts and contribution plans.
A12: 7 | B12: Review dashboard | C12: Use Dashboard, Reports and Smart Calendar for insights.
